ethswarm_deployments/__init__.py
ethswarm_deployments/constants.py
ethswarm_deployments/deployments.py
ethswarm_deployments/exceptions.py
ethswarm_deployments/ingestion.py
ethswarm_deployments/parsers.py
ethswarm_deployments/paths.py
ethswarm_deployments/types.py
ethswarm_deployments/versions.py
ethswarm_deployments-0.2.0.dist-info/METADATA
ethswarm_deployments-0.2.0.dist-info/WHEEL
ethswarm_deployments-0.2.0.dist-info/RECORD
