Metadata-Version: 2.4
Name: ethswarm-deployments
Version: 0.2.0
Summary: Python library for managing Ethswarm smart contract deployment data across all versions and networks
Requires-Python: >=3.10
Requires-Dist: requests>=2.31.0
Provides-Extra: dev
Requires-Dist: pytest>=7.4.0; extra == 'dev'
Requires-Dist: responses>=0.24.0; extra == 'dev'
Requires-Dist: ruff>=0.1.0; extra == 'dev'
